img/img1.png
img/img2.png
img/img3.png
img/img4.png
img/img5.png
img/img6.png
img/img7.png
img/img8.png
seisplot/__init__.py
seisplot/_seisplt.py
seisplot/colormaps.py
seisplot-1.4.0.dist-info/licenses/LICENSE.md
seisplot-1.4.0.dist-info/METADATA
seisplot-1.4.0.dist-info/WHEEL
seisplot-1.4.0.dist-info/top_level.txt
seisplot-1.4.0.dist-info/RECORD
