Metadata-Version: 2.4
Name: seisplot
Version: 1.4.0
Summary: Plotting of seismic data
Author-email: Thomas Hertweck <geophysics@email.de>
Maintainer-email: Thomas Hertweck <geophysics@email.de>
License-Expression: LGPL-3.0-or-later
Project-URL: Repository, https://gitlab.kit.edu/thomas.hertweck/seisplot
Keywords: seismic,display,image,wiggle,variable-density,variable-area,animation,spectrum,amplitude,phase,crossplot,histogram
Classifier: Programming Language :: Python :: 3
Classifier: Operating System :: OS Independent
Requires-Python: >=3.9
License-File: LICENSE.md
Requires-Dist: numpy
Requires-Dist: matplotlib
Provides-Extra: opt
Requires-Dist: pandas; extra == "opt"
Requires-Dist: numba; extra == "opt"
Dynamic: license-file
